{"data":[{"_id":"5ae032b63845ee0079c5aad3","service":"google-cloud","data":{"meta":{"tiers":{"0,25":1,"0,50":0.8,"0,75":0.6,"1,0":0.4},"base":0.25},"services":{"CP-COMPUTEENGINE-VMIMAGE-F1-MICRO":{"locales":{"us":0.0076,"us-central1":0.0076,"us-east1":0.0076,"us-east4":0.0086,"us-west1":0.0076,"europe":0.0086,"europe-west1":0.0086,"europe-west2":0.0096,"europe-west3":0.0096,"europe-west4":0.0084,"northamerica-northeast1":0.0084,"asia":0.009,"asia-east":0.009,"asia-northeast":0.0092,"asia-southeast":0.0092,"australia-southeast1":0.0106,"australia":0.0106,"southamerica-east1":0.0118,"asia-south1":0.0091},"properties":{"cores":"shared","memory":"0.6","gceu":"Shared CPU, not guaranteed","maxNumberOfPd":16,"maxPdSize":64}},"CP-COMPUTEENGINE-VMIMAGE-G1-SMALL":{"locales":{"us":0.027,"us-central1":0.027,"us-east1":0.027,"us-east4":0.0289,"us-west1":0.027,"europe":0.0285,"europe-west1":0.0285,"europe-west2":0.0324,"europe-west3":0.0324,"europe-west4":0.0283,"northamerica-northeast1":0.0283,"asia":0.03,"asia-east":0.03,"asia-northeast":0.0322,"asia-southeast":0.0311,"australia-southeast1":0.0357,"australia":0.0357,"southamerica-east1":0.04,"asia-south1":0.0308},"properties":{"cores":"shared","memory":"1.7","gceu":1.38,"maxNumberOfPd":16,"maxPdSize":64}},"CP-COMPUTEENGINE-VMIMAGE-N1-STANDARD-1":{"locales":{"us":0.0475,"us-central1":0.0475,"us-east1":0.0475,"us-east4":0.0535,"us-west1":0.0475,"europe":0.0523,"europe-west1":0.0523,"europe-west2":0.0612,"europe-west3":0.0612,"europe-west4":0.0523,"northamerica-northeast1":0.0523,"asia":0.055,"asia-east":0.055,"asia-northeast":0.061,"asia-southeast":0.0586,"australia-southeast1":0.0674,"australia":0.0674,"southamerica-east1":0.0754,"asia-south1":0.057},"properties":{"cores":"1","memory":"3.75","gceu":2.75,"maxNumberOfPd":16,"maxPdSize":64}},"CP-COMPUTEENGINE-VMIMAGE-N1-STANDARD-2":{"locales":{"us":0.095,"us-central1":0.095,"us-east1":0.095,"us-east4":0.107,"us-west1":0.095,"europe":0.1046,"europe-west1":0.1046,"europe-west2":0.1224,"europe-west3":0.1224,"europe-west4":0.1046,"northamerica-northeast1":0.1046,"asia":0.11,"asia-east":0.11,"asia-northeast":0.122,"asia-southeast":0.1172,"australia-southeast1":0.1348,"australia":0.1348,"southamerica-east1":0.1508,"asia-south1":0.1141},"properties":{"cores":"2","memory":"7.5","gceu":5.5,"maxNumberOfPd":16,"maxPdSize":64}},"CP-COMPUTEENGINE-VMIMAGE-N1-STANDARD-4":{"locales":{"us":0.19,"us-central1":0.19,"us-east1":0.19,"us-east4":0.214,"us-west1":0.19,"europe":0.2092,"europe-west1":0.2092,"europe-west2":0.2448,"europe-west3":0.2448,"europe-west4":0.2092,"northamerica-northeast1":0.2092,"asia":0.22,"asia-east":0.22,"asia-northeast":0.244,"asia-southeast":0.2344,"australia-southeast1":0.2697,"australia":0.2697,"southamerica-east1":0.3017,"asia-south1":0.2282},"properties":{"cores":"4","memory":"15","gceu":11,"maxNumberOfPd":16,"maxPdSize":64}},"CP-COMPUTEENGINE-VMIMAGE-N1-STANDARD-8":{"locales":{"us":0.38,"us-central1":0.38,"us-east1":0.38,"us-east4":0.428,"us-west1":0.38,"europe":0.4184,"europe-west1":0.4184,"europe-west2":0.4896,"europe-west3":0.4896,"europe-west4":0.4184,"northamerica-northeast1":0.4184,"asia":0.44,"asia-east":0.44,"asia-northeast":0.488,"asia-southeast":0.4688,"australia-southeast1":0.5393,"australia":0.5393,"southamerica-east1":0.6034,"asia-south1":0.4564},"properties":{"cores":"8","memory":"30","gceu":22,"maxNumberOfPd":16,"maxPdSize":64}},"CP-COMPUTEENGINE-VMIMAGE-N1-STANDARD-16":{"locales":{"us":0.76,"us-central1":0.76,"us-east1":0.76,"us-east4":0.856,"us-west1":0.76,"europe":0.8368,"europe-west1":0.8368,"europe-west2":0.9792,"europe-west3":0.9792,"europe-west4":0.8368,"northamerica-northeast1":0.8368,"asia":0.88,"asia-east":0.88,"asia-northeast":0.976,"asia-southeast":0.9376,"australia-southeast1":1.0787,"australia":1.0787,"southamerica-east1":1.2068,"asia-south1":0.9127},"properties":{"cores":"16","memory":"60","gceu":44,"maxNumberOfPd":16,"maxPdSize":64}},"CP-COMPUTEENGINE-VMIMAGE-N1-STANDARD-32":{"locales":{"us":1.52,"us-central1":1.52,"us-east1":1.52,"us-east4":1.712,"us-west1":1.52,"europe":1.6736,"europe-west1":1.6736,"europe-west2":1.9584,"europe-west3":1.9584,"europe-west4":1.6736,"northamerica-northeast1":1.6736,"asia":1.76,"asia-east":1.76,"asia-northeast":1.952,"asia-southeast":1.8752,"australia-southeast1":2.1574,"australia":2.1574,"southamerica-east1":2.4136,"asia-south1":1.8255},"properties":{"cores":"32","memory":"120","gceu":88,"maxNumberOfPd":16,"maxPdSize":64}},"CP-COMPUTEENGINE-VMIMAGE-N1-STANDARD-64":{"locales":{"us":3.04,"us-central1":3.04,"us-east1":3.04,"us-east4":3.424,"us-west1":3.04,"europe":3.3472,"europe-west1":3.3472,"europe-west2":3.9168,"europe-west3":3.9168,"europe-west4":3.3472,"northamerica-northeast1":3.3472,"asia":3.52,"asia-east":3.52,"asia-northeast":3.904,"asia-southeast":3.7504,"australia-southeast1":4.3147,"australia":4.3147,"southamerica-east1":4.8271,"asia-south1":3.651},"properties":{"cores":"64","memory":"240","gceu":176,"maxNumberOfPd":16,"maxPdSize":64}},"CP-COMPUTEENGINE-VMIMAGE-N1-STANDARD-96":{"locales":{"us":4.56,"us-central1":4.56,"us-east1":4.56,"us-east4":5.136,"us-west1":4.56,"europe":5.0208,"europe-west1":5.0208,"europe-west2":5.8752,"europe-west3":5.8752,"europe-west4":5.020032,"northamerica-northeast1":5.020032,"asia":5.28,"asia-east":5.28,"asia-northeast":5.856,"asia-southeast":5.6256,"australia-southeast1":6.48,"australia":6.48,"southamerica-east1":7.24068,"asia-south1":5.48},"properties":{"cores":"96","memory":"360","gceu":264,"maxNumberOfPd":16,"maxPdSize":64}},"CP-COMPUTEENGINE-VMIMAGE-N1-HIGHMEM-2":{"locales":{"us":0.1184,"us-central1":0.1184,"us-east1":0.1184,"us-east4":0.1348,"us-west1":0.1184,"europe":0.1302,"europe-west1":0.1302,"europe-west2":0.1523,"europe-west3":0.1523,"europe-west4":0.1303,"northamerica-northeast1":0.1303,"asia":0.137,"asia-east":0.137,"asia-northeast":0.1517,"asia-southeast":0.146,"australia-southeast1":0.1679,"australia":0.1679,"southamerica-east1":0.1879,"asia-south1":0.1421},"properties":{"cores":"2","memory":"13","gceu":5.5,"maxNumberOfPd":16,"maxPdSize":64}},"CP-COMPUTEENGINE-VMIMAGE-N1-HIGHMEM-4":{"locales":{"us":0.2368,"us-central1":0.2368,"us-east1":0.2368,"us-east4":0.2696,"us-west1":0.2368,"europe":0.2604,"europe-west1":0.2604,"europe-west2":0.3046,"europe-west3":0.3046,"europe-west4":0.2606,"northamerica-northeast1":0.2606,"asia":0.274,"asia-east":0.274,"asia-northeast":0.3034,"asia-southeast":0.292,"australia-southeast1":0.3358,"australia":0.3358,"southamerica-east1":0.3757,"asia-south1":0.2842},"properties":{"cores":"4","memory":"26","gceu":11,"maxNumberOfPd":16,"maxPdSize":64}},"CP-COMPUTEENGINE-VMIMAGE-N1-HIGHMEM-8":{"locales":{"us":0.4736,"us-central1":0.4736,"us-east1":0.4736,"us-east4":0.5393,"us-west1":0.4736,"europe":0.5208,"europe-west1":0.5208,"europe-west2":0.6092,"europe-west3":0.6092,"europe-west4":0.5212,"northamerica-northeast1":0.5212,"asia":0.548,"asia-east":0.548,"asia-northeast":0.6068,"asia-southeast":0.584,"australia-southeast1":0.6716,"australia":0.6716,"southamerica-east1":0.7514,"asia-south1":0.5683},"properties":{"cores":"8","memory":"52","gceu":22,"maxNumberOfPd":16,"maxPdSize":64}},"CP-COMPUTEENGINE-VMIMAGE-N1-HIGHMEM-16":{"locales":{"us":0.9472,"us-central1":0.9472,"us-east1":0.9472,"us-east4":1.0786,"us-west1":0.9472,"europe":1.0416,"europe-west1":1.0416,"europe-west2":1.2184,"europe-west3":1.2184,"europe-west4":1.0424,"northamerica-northeast1":1.0424,"asia":1.096,"asia-east":1.096,"asia-northeast":1.2136,"asia-southeast":1.168,"australia-southeast1":1.3431,"australia":1.3431,"southamerica-east1":1.5029,"asia-south1":1.1366},"properties":{"cores":"16","memory":"104","gceu":44,"maxNumberOfPd":16,"maxPdSize":64}},"CP-COMPUTEENGINE-VMIMAGE-N1-HIGHMEM-32":{"locales":{"us":1.8944,"us-central1":1.8944,"us-east1":1.8944,"us-east4":2.1571,"us-west1":1.8944,"europe":2.0832,"europe-west1":2.0832,"europe-west2":2.4368,"europe-west3":2.4368,"europe-west4":2.0848,"northamerica-northeast1":2.0848,"asia":2.192,"asia-east":2.192,"asia-northeast":2.4272,"asia-southeast":2.336,"australia-southeast1":2.6862,"australia":2.6862,"southamerica-east1":3.0057,"asia-south1":2.2732},"properties":{"cores":"32","memory":"208","gceu":88,"maxNumberOfPd":16,"maxPdSize":64}},"CP-COMPUTEENGINE-VMIMAGE-N1-HIGHMEM-64":{"locales":{"us":3.7888,"us-central1":3.7888,"us-east1":3.7888,"us-east4":4.3142,"us-west1":3.7888,"europe":4.1664,"europe-west1":4.1664,"europe-west2":4.8736,"europe-west3":4.8736,"europe-west4":4.1696,"northamerica-northeast1":4.1696,"asia":4.384,"asia-east":4.384,"asia-northeast":4.8544,"asia-southeast":4.672,"australia-southeast1":5.3725,"australia":5.3725,"southamerica-east1":6.0114,"asia-south1":4.5465},"properties":{"cores":"64","memory":"416","gceu":176,"maxNumberOfPd":16,"maxPdSize":64}},"CP-COMPUTEENGINE-VMIMAGE-N1-HIGHMEM-96":{"locales":{"us":5.6832,"us-central1":5.6832,"us-east1":5.6832,"us-east4":6.4716,"us-west1":5.6832,"europe":6.2496,"europe-west1":6.2496,"europe-west2":7.3104,"europe-west3":7.3104,"europe-west4":6.251328,"northamerica-northeast1":6.251328,"asia":6.576,"asia-east":6.576,"asia-northeast":7.2816,"asia-southeast":7.008,"australia-southeast1":8.0592,"australia":8.0592,"southamerica-east1":9.017136,"asia-south1":6.82},"properties":{"cores":"96","memory":"624","gceu":264,"maxNumberOfPd":16,"maxPdSize":64}},"CP-COMPUTEENGINE-VMIMAGE-N1-HIGHCPU-2":{"locales":{"us":0.0709,"us-central1":0.0709,"us-east1":0.0709,"us-east4":0.0813,"us-west1":0.0709,"europe":0.078,"europe-west1":0.078,"europe-west2":0.0912,"europe-west3":0.0912,"europe-west4":0.0781,"northamerica-northeast1":0.0781,"asia":0.0821,"asia-east":0.0821,"asia-northeast":0.091,"asia-southeast":0.0874,"australia-southeast1":0.1006,"australia":0.1006,"southamerica-east1":0.1125,"asia-south1":0.0851},"properties":{"cores":"2","memory":"1.8","gceu":5.5,"maxNumberOfPd":16,"maxPdSize":64}},"CP-COMPUTEENGINE-VMIMAGE-N1-HIGHCPU-4":{"locales":{"us":0.1418,"us-central1":0.1418,"us-east1":0.1418,"us-east4":0.1626,"us-west1":0.1418,"europe":0.156,"europe-west1":0.156,"europe-west2":0.1824,"europe-west3":0.1824,"europe-west4":0.1562,"northamerica-northeast1":0.1562,"asia":0.1642,"asia-east":0.1642,"asia-northeast":0.182,"asia-southeast":0.1748,"australia-southeast1":0.2012,"australia":0.2012,"southamerica-east1":0.225,"asia-south1":0.1702},"properties":{"cores":"4","memory":"3.6","gceu":11,"maxNumberOfPd":16,"maxPdSize":64}},"CP-COMPUTEENGINE-VMIMAGE-N1-HIGHCPU-8":{"locales":{"us":0.2836,"us-central1":0.2836,"us-east1":0.2836,"us-east4":0.3253,"us-west1":0.2836,"europe":0.312,"europe-west1":0.312,"europe-west2":0.3648,"europe-west3":0.3648,"europe-west4":0.3124,"northamerica-northeast1":0.3124,"asia":0.3284,"asia-east":0.3284,"asia-northeast":0.364,"asia-southeast":0.3496,"australia-southeast1":0.4023,"australia":0.4023,"southamerica-east1":0.45,"asia-south1":0.3404},"properties":{"cores":"8","memory":"7.2","gceu":22,"maxNumberOfPd":16,"maxPdSize":64}},"CP-COMPUTEENGINE-VMIMAGE-N1-HIGHCPU-16":{"locales":{"us":0.5672,"us-central1":0.5672,"us-east1":0.5672,"us-east4":0.6506,"us-west1":0.5672,"europe":0.624,"europe-west1":0.624,"europe-west2":0.7296,"europe-west3":0.7296,"europe-west4":0.6248,"northamerica-northeast1":0.6248,"asia":0.6568,"asia-east":0.6568,"asia-northeast":0.728,"asia-southeast":0.6992,"australia-southeast1":0.8046,"australia":0.8046,"southamerica-east1":0.8999,"asia-south1":0.6807},"properties":{"cores":"16","memory":"14.40","gceu":44,"maxNumberOfPd":16,"maxPdSize":64}},"CP-COMPUTEENGINE-VMIMAGE-N1-HIGHCPU-32":{"locales":{"us":1.1344,"us-central1":1.1344,"us-east1":1.1344,"us-east4":1.3011,"us-west1":1.1344,"europe":1.248,"europe-west1":1.248,"europe-west2":1.4592,"europe-west3":1.4592,"europe-west4":1.2496,"northamerica-northeast1":1.2496,"asia":1.3136,"asia-east":1.3136,"asia-northeast":1.456,"asia-southeast":1.3984,"australia-southeast1":1.6092,"australia":1.6092,"southamerica-east1":1.7999,"asia-south1":1.3615},"properties":{"cores":"32","memory":"28.80","gceu":88,"maxNumberOfPd":16,"maxPdSize":64}},"CP-COMPUTEENGINE-VMIMAGE-N1-HIGHCPU-64":{"locales":{"us":2.2688,"us-central1":2.2688,"us-east1":2.2688,"us-east4":2.6022,"us-west1":2.2688,"europe":2.496,"europe-west1":2.496,"europe-west2":2.9184,"europe-west3":2.9184,"europe-west4":2.4992,"northamerica-northeast1":2.4992,"asia":2.6272,"asia-east":2.6272,"asia-northeast":2.912,"asia-southeast":2.7968,"australia-southeast1":3.2185,"australia":3.2185,"southamerica-east1":3.5998,"asia-south1":2.7229},"properties":{"cores":"64","memory":"57.6","gceu":176,"maxNumberOfPd":16,"maxPdSize":64}},"CP-COMPUTEENGINE-VMIMAGE-N1-HIGHCPU-96":{"locales":{"us":3.4032,"us-central1":3.4032,"us-east1":3.4032,"us-east4":3.9036,"us-west1":3.4032,"europe":3.744,"europe-west1":3.744,"europe-west2":4.3776,"europe-west3":4.3776,"europe-west4":3.743962,"northamerica-northeast1":3.7439616,"asia":3.9408,"asia-east":3.9408,"asia-northeast":4.368,"asia-southeast":4.1952,"australia-southeast1":4.8288,"australia":4.8288,"southamerica-east1":5.399625,"asia-south1":4.08},"properties":{"cores":"96","memory":"86.4","gceu":264,"maxNumberOfPd":16,"maxPdSize":64}},"CP-COMPUTEENGINE-VMIMAGE-N1-MEGAMEM-96":{"locales":{"us":10.67,"us-central1":10.67,"us-east1":0,"us-east4":0,"us-west1":10.67,"europe":11.74,"europe-west1":11.74,"europe-west2":0,"europe-west3":0,"europe-west4":0,"northamerica-northeast1":0,"asia":12.36,"asia-east":12.36,"asia-northeast":0,"asia-southeast":0,"australia-southeast1":0,"australia":0,"southamerica-east1":0,"asia-south1":0},"properties":{"cores":"96","memory":"1440","gceu":264,"maxNumberOfPd":16,"maxPdSize":64}},"CP-COMPUTEENGINE-VMIMAGE-F1-MICRO-PREEMPTIBLE":{"locales":{"us":0.0035,"us-central1":0.0035,"us-east1":0.0035,"us-east4":0.00375,"us-west1":0.0035,"europe":0.0039,"europe-west1":0.0039,"europe-west2":0.0042,"europe-west3":0.0042,"europe-west4":0.0039,"northamerica-northeast1":0.0039,"asia":0.0039,"asia-east":0.0039,"asia-northeast":0.005,"asia-southeast":0.004,"australia-southeast1":0.0046,"australia":0.0046,"southamerica-east1":0.0052,"asia-south1":0.0042},"properties":{"cores":"shared","memory":"0.6"}},"CP-COMPUTEENGINE-VMIMAGE-G1-SMALL-PREEMPTIBLE":{"locales":{"us":0.007,"us-central1":0.007,"us-east1":0.007,"us-east4":0.00749,"us-west1":0.007,"europe":0.0077,"europe-west1":0.0077,"europe-west2":0.0084,"europe-west3":0.0084,"europe-west4":0.0077,"northamerica-northeast1":0.0077,"asia":0.0077,"asia-east":0.0077,"asia-northeast":0.01,"asia-southeast":0.0081,"australia-southeast1":0.0093,"australia":0.0093,"southamerica-east1":0.0104,"asia-south1":0.0084},"properties":{"cores":"shared","memory":"1.7"}},"CP-COMPUTEENGINE-VMIMAGE-N1-STANDARD-1-PREEMPTIBLE":{"locales":{"us":0.01,"us-central1":0.01,"us-east1":0.01,"us-east4":0.0107,"us-west1":0.01,"europe":0.011,"europe-west1":0.011,"europe-west2":0.0123,"europe-west3":0.0123,"europe-west4":0.011,"northamerica-northeast1":0.011,"asia":0.011,"asia-east":0.011,"asia-northeast":0.01325,"asia-southeast":0.0118,"australia-southeast1":0.01349,"australia":0.01349,"southamerica-east1":0.0151,"asia-south1":0.01203},"properties":{"cores":"1","memory":"3.75"}},"CP-COMPUTEENGINE-VMIMAGE-N1-STANDARD-2-PREEMPTIBLE":{"locales":{"us":0.02,"us-central1":0.02,"us-east1":0.02,"us-east4":0.0214,"us-west1":0.02,"europe":0.022,"europe-west1":0.022,"europe-west2":0.0246,"europe-west3":0.0246,"europe-west4":0.0221,"northamerica-northeast1":0.0221,"asia":0.022,"asia-east":0.022,"asia-northeast":0.0265,"asia-southeast":0.0236,"australia-southeast1":0.02698,"australia":0.02698,"southamerica-east1":0.0302,"asia-south1":0.02405},"properties":{"cores":"2","memory":"7.5"}},"CP-COMPUTEENGINE-VMIMAGE-N1-STANDARD-4-PREEMPTIBLE":{"locales":{"us":0.04,"us-central1":0.04,"us-east1":0.04,"us-east4":0.0428,"us-west1":0.04,"europe":0.044,"europe-west1":0.044,"europe-west2":0.0492,"europe-west3":0.0492,"europe-west4":0.0441,"northamerica-northeast1":0.0441,"asia":0.044,"asia-east":0.044,"asia-northeast":0.053,"asia-southeast":0.0472,"australia-southeast1":0.05397,"australia":0.05397,"southamerica-east1":0.0604,"asia-south1":0.04811},"properties":{"cores":"4","memory":"15"}},"CP-COMPUTEENGINE-VMIMAGE-N1-STANDARD-8-PREEMPTIBLE":{"locales":{"us":0.08,"us-central1":0.08,"us-east1":0.08,"us-east4":0.0856,"us-west1":0.08,"europe":0.088,"europe-west1":0.088,"europe-west2":0.0984,"europe-west3":0.0984,"europe-west4":0.0882,"northamerica-northeast1":0.0882,"asia":0.088,"asia-east":0.088,"asia-northeast":0.106,"asia-southeast":0.0944,"australia-southeast1":0.10793,"australia":0.10793,"southamerica-east1":0.1208,"asia-south1":0.09622},"properties":{"cores":"8","memory":"30"}},"CP-COMPUTEENGINE-VMIMAGE-N1-STANDARD-16-PREEMPTIBLE":{"locales":{"us":0.16,"us-central1":0.16,"us-east1":0.16,"us-east4":0.1712,"us-west1":0.16,"europe":0.176,"europe-west1":0.176,"europe-west2":0.1968,"europe-west3":0.1968,"europe-west4":0.1764,"northamerica-northeast1":0.1764,"asia":0.176,"asia-east":0.176,"asia-northeast":0.212,"asia-southeast":0.1888,"australia-southeast1":0.21586,"australia":0.21586,"southamerica-east1":0.2416,"asia-south1":0.19243},"properties":{"cores":"16","memory":"60"}},"CP-COMPUTEENGINE-VMIMAGE-N1-STANDARD-32-PREEMPTIBLE":{"locales":{"us":0.32,"us-central1":0.32,"us-east1":0.32,"us-east4":0.3424,"us-west1":0.32,"europe":0.352,"europe-west1":0.352,"europe-west2":0.3936,"europe-west3":0.3936,"europe-west4":0.3528,"northamerica-northeast1":0.3528,"asia":0.352,"asia-east":0.352,"asia-northeast":0.424,"asia-southeast":0.3776,"australia-southeast1":0.43172,"australia":0.43172,"southamerica-east1":0.4832,"asia-south1":0.38486},"properties":{"cores":"32","memory":"120"}},"CP-COMPUTEENGINE-VMIMAGE-N1-STANDARD-64-PREEMPTIBLE":{"locales":{"us":0.64,"us-central1":0.64,"us-east1":0.64,"us-east4":0.6848,"us-west1":0.64,"europe":0.704,"europe-west1":0.704,"europe-west2":0.7872,"europe-west3":0.7872,"europe-west4":0.7057,"northamerica-northeast1":0.7057,"asia":0.704,"asia-east":0.704,"asia-northeast":0.848,"asia-southeast":0.7552,"australia-southeast1":0.86344,"australia":0.86344,"southamerica-east1":0.9664,"asia-south1":0.76973},"properties":{"cores":"64","memory":"240"}},"CP-COMPUTEENGINE-VMIMAGE-N1-STANDARD-96-PREEMPTIBLE":{"locales":{"us":0.96,"us-central1":0.96,"us-east1":0.96,"us-east4":1.0272,"us-west1":0.96,"europe":1.056,"europe-west1":1.056,"europe-west2":1.1808,"europe-west3":1.1808,"europe-west4":1.05852,"northamerica-northeast1":1.05852,"asia":1.056,"asia-east":1.056,"asia-northeast":1.272,"asia-southeast":1.1328,"australia-southeast1":1.296,"australia":1.296,"southamerica-east1":1.4496,"asia-south1":0.96},"properties":{"cores":"96","memory":"360"}},"CP-COMPUTEENGINE-VMIMAGE-N1-HIGHMEM-2-PREEMPTIBLE":{"locales":{"us":0.025,"us-central1":0.025,"us-east1":0.025,"us-east4":0.02675,"us-west1":0.025,"europe":0.0275,"europe-west1":0.0275,"europe-west2":0.0305,"europe-west3":0.0305,"europe-west4":0.0275,"northamerica-northeast1":0.0275,"asia":0.0275,"asia-east":0.0275,"asia-northeast":0.033,"asia-southeast":0.0292,"australia-southeast1":0.0336,"australia":0.0336,"southamerica-east1":0.03757,"asia-south1":0.02997},"properties":{"cores":"2","memory":"13"}},"CP-COMPUTEENGINE-VMIMAGE-N1-HIGHMEM-4-PREEMPTIBLE":{"locales":{"us":0.05,"us-central1":0.05,"us-east1":0.05,"us-east4":0.0535,"us-west1":0.05,"europe":0.055,"europe-west1":0.055,"europe-west2":0.061,"europe-west3":0.061,"europe-west4":0.055,"northamerica-northeast1":0.055,"asia":0.055,"asia-east":0.055,"asia-northeast":0.066,"asia-southeast":0.0584,"australia-southeast1":0.0672,"australia":0.0672,"southamerica-east1":0.07515,"asia-south1":0.05994},"properties":{"cores":"4","memory":"26"}},"CP-COMPUTEENGINE-VMIMAGE-N1-HIGHMEM-8-PREEMPTIBLE":{"locales":{"us":0.1,"us-central1":0.1,"us-east1":0.1,"us-east4":0.107,"us-west1":0.1,"europe":0.11,"europe-west1":0.11,"europe-west2":0.122,"europe-west3":0.122,"europe-west4":0.1099,"northamerica-northeast1":0.1099,"asia":0.11,"asia-east":0.11,"asia-northeast":0.132,"asia-southeast":0.1168,"australia-southeast1":0.1344,"australia":0.1344,"southamerica-east1":0.1503,"asia-south1":0.11989},"properties":{"cores":"8","memory":"52"}},"CP-COMPUTEENGINE-VMIMAGE-N1-HIGHMEM-16-PREEMPTIBLE":{"locales":{"us":0.2,"us-central1":0.2,"us-east1":0.2,"us-east4":0.214,"us-west1":0.2,"europe":0.22,"europe-west1":0.22,"europe-west2":0.244,"europe-west3":0.244,"europe-west4":0.2198,"northamerica-northeast1":0.2198,"asia":0.22,"asia-east":0.22,"asia-northeast":0.264,"asia-southeast":0.2336,"australia-southeast1":0.26879,"australia":0.26879,"southamerica-east1":0.30059,"asia-south1":0.23978},"properties":{"cores":"16","memory":"104"}},"CP-COMPUTEENGINE-VMIMAGE-N1-HIGHMEM-32-PREEMPTIBLE":{"locales":{"us":0.4,"us-central1":0.4,"us-east1":0.4,"us-east4":0.428,"us-west1":0.4,"europe":0.44,"europe-west1":0.44,"europe-west2":0.488,"europe-west3":0.488,"europe-west4":0.4397,"northamerica-northeast1":0.4397,"asia":0.44,"asia-east":0.44,"asia-northeast":0.528,"asia-southeast":0.4672,"australia-southeast1":0.53758,"australia":0.53758,"southamerica-east1":0.60118,"asia-south1":0.47955},"properties":{"cores":"32","memory":"208"}},"CP-COMPUTEENGINE-VMIMAGE-N1-HIGHMEM-64-PREEMPTIBLE":{"locales":{"us":0.8,"us-central1":0.8,"us-east1":0.8,"us-east4":0.856,"us-west1":0.8,"europe":0.88,"europe-west1":0.88,"europe-west2":0.976,"europe-west3":0.976,"europe-west4":0.8793,"northamerica-northeast1":0.8793,"asia":0.88,"asia-east":0.88,"asia-northeast":1.056,"asia-southeast":0.9344,"australia-southeast1":1.07517,"australia":1.07517,"southamerica-east1":1.20237,"asia-south1":0.9591},"properties":{"cores":"64","memory":"416"}},"CP-COMPUTEENGINE-VMIMAGE-N1-HIGHMEM-96-PREEMPTIBLE":{"locales":{"us":1.2,"us-central1":1.2,"us-east1":1.2,"us-east4":1.284,"us-west1":1.2,"europe":1.32,"europe-west1":1.32,"europe-west2":1.464,"europe-west3":1.464,"europe-west4":1.319088,"northamerica-northeast1":1.319088,"asia":1.32,"asia-east":1.32,"asia-northeast":1.584,"asia-southeast":1.4016,"australia-southeast1":1.6128,"australia":1.6128,"southamerica-east1":1.803552,"asia-south1":1.2},"properties":{"cores":"96","memory":"624"}},"CP-COMPUTEENGINE-VMIMAGE-N1-HIGHCPU-2-PREEMPTIBLE":{"locales":{"us":0.015,"us-central1":0.015,"us-east1":0.015,"us-east4":0.01605,"us-west1":0.015,"europe":0.0165,"europe-west1":0.0165,"europe-west2":0.0183,"europe-west3":0.0183,"europe-west4":0.0164,"northamerica-northeast1":0.0164,"asia":0.0165,"asia-east":0.0165,"asia-northeast":0.0198,"asia-southeast":0.0175,"australia-southeast1":0.02013,"australia":0.02013,"southamerica-east1":0.0225,"asia-south1":0.01792},"properties":{"cores":"2","memory":"1.8"}},"CP-COMPUTEENGINE-VMIMAGE-N1-HIGHCPU-4-PREEMPTIBLE":{"locales":{"us":0.03,"us-central1":0.03,"us-east1":0.03,"us-east4":0.0321,"us-west1":0.03,"europe":0.033,"europe-west1":0.033,"europe-west2":0.0366,"europe-west3":0.0366,"europe-west4":0.0329,"northamerica-northeast1":0.0329,"asia":0.033,"asia-east":0.033,"asia-northeast":0.0396,"asia-southeast":0.035,"australia-southeast1":0.04025,"australia":0.04025,"southamerica-east1":0.045,"asia-south1":0.03584},"properties":{"cores":"4","memory":"3.6"}},"CP-COMPUTEENGINE-VMIMAGE-N1-HIGHCPU-8-PREEMPTIBLE":{"locales":{"us":0.06,"us-central1":0.06,"us-east1":0.06,"us-east4":0.0642,"us-west1":0.06,"europe":0.066,"europe-west1":0.066,"europe-west2":0.0732,"europe-west3":0.0732,"europe-west4":0.0657,"northamerica-northeast1":0.0657,"asia":0.066,"asia-east":0.066,"asia-northeast":0.0792,"asia-southeast":0.07,"australia-southeast1":0.0805,"australia":0.0805,"southamerica-east1":0.09,"asia-south1":0.07168},"properties":{"cores":"8","memory":"7.2"}},"CP-COMPUTEENGINE-VMIMAGE-N1-HIGHCPU-16-PREEMPTIBLE":{"locales":{"us":0.12,"us-central1":0.12,"us-east1":0.12,"us-east4":0.1284,"us-west1":0.12,"europe":0.132,"europe-west1":0.132,"europe-west2":0.1464,"europe-west3":0.1464,"europe-west4":0.1314,"northamerica-northeast1":0.1314,"asia":0.132,"asia-east":0.132,"asia-northeast":0.1584,"asia-southeast":0.14,"australia-southeast1":0.161,"australia":0.161,"southamerica-east1":0.17999,"asia-south1":0.14337},"properties":{"cores":"16","memory":"14.40"}},"CP-COMPUTEENGINE-VMIMAGE-N1-HIGHCPU-32-PREEMPTIBLE":{"locales":{"us":0.24,"us-central1":0.24,"us-east1":0.24,"us-east4":0.2568,"us-west1":0.24,"europe":0.264,"europe-west1":0.264,"europe-west2":0.2928,"europe-west3":0.2928,"europe-west4":0.2629,"northamerica-northeast1":0.2629,"asia":0.264,"asia-east":0.264,"asia-northeast":0.3168,"asia-southeast":0.28,"australia-southeast1":0.32201,"australia":0.32201,"southamerica-east1":0.35998,"asia-south1":0.28673},"properties":{"cores":"32","memory":"28.80"}},"CP-COMPUTEENGINE-VMIMAGE-N1-HIGHCPU-64-PREEMPTIBLE":{"locales":{"us":0.48,"us-central1":0.48,"us-east1":0.48,"us-east4":0.5136,"us-west1":0.48,"europe":0.528,"europe-west1":0.528,"europe-west2":0.5856,"europe-west3":0.5856,"europe-west4":0.5257,"northamerica-northeast1":0.5257,"asia":0.528,"asia-east":0.528,"asia-northeast":0.6336,"asia-southeast":0.56,"australia-southeast1":0.64401,"australia":0.64401,"southamerica-east1":0.71996,"asia-south1":0.57347},"properties":{"cores":"64","memory":"57.6"}},"CP-COMPUTEENGINE-VMIMAGE-N1-HIGHCPU-96-PREEMPTIBLE":{"locales":{"us":0.72,"us-central1":0.72,"us-east1":0.72,"us-east4":0.7704,"us-west1":0.72,"europe":0.792,"europe-west1":0.792,"europe-west2":0.8784,"europe-west3":0.8784,"europe-west4":0.7884768,"northamerica-northeast1":0.7884768,"asia":0.792,"asia-east":0.792,"asia-northeast":0.9504,"asia-southeast":0.84,"australia-southeast1":0.9696,"australia":0.9696,"southamerica-east1":1.079943,"asia-south1":0.72},"properties":{"cores":"96","memory":"86.4"}},"CP-COMPUTEENGINE-VMIMAGE-N1-MEGAMEM-96-PREEMPTIBLE":{"locales":{"us":2.26,"us-central1":2.26,"us-east1":0,"us-east4":0,"us-west1":2.26,"europe":2.47,"europe-west1":2.47,"europe-west2":0,"europe-west3":0,"europe-west4":0,"northamerica-northeast1":0,"asia":2.47,"asia-east":2.47,"asia-northeast":0,"asia-southeast":0,"australia-southeast1":0,"australia":0,"southamerica-east1":0,"asia-south1":0},"properties":{"cores":"96","memory":"1440"}},"CP-COMPUTEENGINE-LOCAL-SSD":{"locales":{"us":0.00010959,"us-central1":0.00010959,"us-east1":0.00010959,"us-east4":0.00012055,"us-west1":0.00010959,"europe":0.00010959,"europe-west1":0.00010959,"europe-west2":0.00013151,"europe-west3":0.00013151,"europe-west4":0.00012055,"northamerica-northeast1":0.00012055,"asia":0.00010959,"asia-east":0.00010959,"asia-northeast":0.00014247,"asia-southeast":0.00012055,"australia-southeast1":0.00014795,"australia":0.00014795,"southamerica-east1":0.000164385,"asia-south1":0.00013151},"properties":{}},"CP-COMPUTEENGINE-LOCAL-SSD-PREEMPTIBLE":{"locales":{"us":0.000065754,"us-central1":0.000065754,"us-east1":0.000065754,"us-east4":0.00009589,"us-west1":0.000065754,"europe":0.000065754,"europe-west1":0.000065754,"europe-west2":0.000079453,"europe-west3":0.000079453,"europe-west4":0.00009589,"northamerica-northeast1":0.00009589,"asia":0.000065754,"asia-east":0.000065754,"asia-northeast":0.000084932,"asia-southeast":0.00009589,"australia-southeast1":0.0000890411,"australia":0.0000890411,"southamerica-east1":0.000098631,"asia-south1":0.000079453},"properties":{}},"CP-COMPUTEENGINE-STORAGE-PD-CAPACITY":{"locales":{"us":0.04,"us-central1":0.04,"us-east1":0.04,"us-east4":0.044,"us-west1":0.04,"europe":0.04,"europe-west1":0.04,"europe-west2":0.048,"europe-west3":0.048,"europe-west4":0.044,"northamerica-northeast1":0.044,"asia-east":0.04,"asia-northeast":0.052,"asia-southeast":0.044,"australia-southeast1":0.054,"australia":0.054,"southamerica-east1":0.06,"asia-south1":0.048},"properties":{}},"CP-COMPUTEENGINE-STORAGE-PD-SSD":{"locales":{"us":0.17,"us-central1":0.17,"us-east1":0.17,"us-east4":0.187,"us-west1":0.17,"europe":0.17,"europe-west1":0.17,"europe-west2":0.204,"europe-west3":0.204,"europe-west4":0.187,"northamerica-northeast1":0.187,"asia-east":0.17,"asia-northeast":0.221,"asia-southeast":0.187,"australia-southeast1":0.23,"australia":0.23,"southamerica-east1":0.255,"asia-south1":0.204},"properties":{}},"CP-COMPUTEENGINE-PD-IO-REQUEST":{"locales":{"us":0},"properties":{}},"CP-COMPUTEENGINE-STORAGE-PD-SNAPSHOT":{"locales":{"us":0.026,"us-central1":0.026,"us-east1":0.026,"us-east4":0.029,"us-west1":0.026,"europe":0.026,"europe-west1":0.026,"europe-west2":0.031,"europe-west3":0.031,"europe-west4":0.029,"northamerica-northeast1":0.029,"asia-east":0.026,"asia-northeast":0.034,"asia-southeast":0.039,"australia-southeast1":0.035,"australia":0.035,"southamerica-east1":0.039,"asia-south1":0.031},"properties":{}},"CP-BIGSTORE-CLASS-A-REQUEST":{"locales":{"us":0.05,"us-central1":0.05,"us-east1":0.05,"us-east4":0.05,"us-west1":0.05,"europe":0.05,"europe-west1":0.05,"europe-west2":0.05,"europe-west3":0.05,"europe-west4":0.05,"northamerica-northeast1":0.05,"asia-east":0.05,"asia-northeast":0.05,"asia-southeast":0.05,"australia-southeast1":0.05,"australia":0.05,"southamerica-east1":0.05,"asia-south1":0.05},"properties":{}},"CP-BIGSTORE-CLASS-B-REQUEST":{"locales":{"us":0.004,"us-central1":0.004,"us-east1":0.004,"us-east4":0.004,"us-west1":0.004,"europe":0.004,"europe-west1":0.004,"europe-west2":0.004,"europe-west3":0.004,"europe-west4":0.004,"northamerica-northeast1":0.004,"asia-east":0.004,"asia-northeast":0.004,"asia-southeast":0.004,"australia-southeast1":0.004,"australia":0.004,"asia-south1":0.004},"properties":{}},"CP-CLOUDSQL-PERUSE-D0":{"locales":{"us":0.025},"properties":{}},"CP-CLOUDSQL-PERUSE-D1":{"locales":{"us":0.1},"properties":{}},"CP-CLOUDSQL-PERUSE-D2":{"locales":{"us":0.19},"properties":{}},"CP-CLOUDSQL-PERUSE-D4":{"locales":{"us":0.29},"properties":{}},"CP-CLOUDSQL-PERUSE-D8":{"locales":{"us":0.58},"properties":{}},"CP-CLOUDSQL-PERUSE-D16":{"locales":{"us":1.16},"properties":{}},"CP-CLOUDSQL-PERUSE-D32":{"locales":{"us":2.31},"properties":{}},"CP-CLOUDSQL-PACKAGE-D0":{"locales":{"us":0.36},"properties":{}},"CP-CLOUDSQL-PACKAGE-D1":{"locales":{"us":1.46},"properties":{}},"CP-CLOUDSQL-PACKAGE-D2":{"locales":{"us":2.93},"properties":{}},"CP-CLOUDSQL-PACKAGE-D4":{"locales":{"us":4.4},"properties":{}},"CP-CLOUDSQL-PACKAGE-D8":{"locales":{"us":8.78},"properties":{}},"CP-CLOUDSQL-PACKAGE-D16":{"locales":{"us":17.57},"properties":{}},"CP-CLOUDSQL-PACKAGE-D32":{"locales":{"us":35.13},"properties":{}},"CP-CLOUDSQL-STORAGE":{"locales":{"us":0.24},"properties":{}},"CP-CLOUDSQL-TRAFFIC":{"locales":{"us":0.12},"properties":{}},"CP-CLOUDSQL-IO":{"locales":{"us":0.1},"properties":{}},"CP-BIGSTORE-STORAGE":{"locales":{"us":0.026},"properties":{}},"CP-BIGSTORE-STORAGE-DRA":{"locales":{"us":0.02},"properties":{}},"CP-NEARLINE-STORAGE":{"locales":{"us":0.01,"us-central1":0.01,"us-east1":0.01,"us-east4":0.016,"us-west1":0.01,"europe":0.01,"europe-west1":0.01,"europe-west2":0.016,"europe-west3":0.016,"europe-west4":0.01,"northamerica-northeast1":0.016,"asia-east":0.01,"asia-northeast":0.016,"asia-southeast":0.01,"australia-southeast1":0.016,"australia":0.016,"southamerica-east1":0.02,"asia-south1":0.016},"properties":{}},"CP-NEARLINE-RESTORE-SIZE":{"locales":{"us":0.01},"properties":{}},"CP-COMPUTEENGINE-INTERCONNECT-US-US":{"locales":{"us":0.04},"properties":{}},"CP-COMPUTEENGINE-INTERCONNECT-EU-EU":{"locales":{"us":0.05},"properties":{}},"CP-COMPUTEENGINE-INTERCONNECT-APAC-APAC":{"locales":{"us":0.06},"properties":{}},"CP-COMPUTEENGINE-INTERNET-EGRESS-ZONE":{"locales":{"us":0.01},"properties":{}},"CP-COMPUTEENGINE-INTERNET-EGRESS-REGION":{"locales":{"us":0.01},"properties":{}},"CP-APP-ENGINE-INSTANCES":{"locales":{"us":0.05},"properties":{}},"CP-APP-ENGINE-OUTGOING-TRAFFIC":{"locales":{"us":0.12},"properties":{}},"CP-APP-ENGINE-CLOUD-STORAGE":{"locales":{"us":0.026},"properties":{}},"CP-APP-ENGINE-MEMCACHE":{"locales":{"us":0.06},"properties":{}},"CP-APP-ENGINE-SEARCH":{"locales":{"us":0.00005},"properties":{}},"CP-APP-ENGINE-INDEXING-DOCUMENTS":{"locales":{"us":2},"properties":{}},"CP-APP-ENGINE-DOCUMENT-STORAGE":{"locales":{"us":0.18},"properties":{}},"CP-APP-ENGINE-LOGS-API":{"locales":{"us":0.12},"properties":{}},"CP-APP-ENGINE-TASK-QUEUE":{"locales":{"us":0.026},"properties":{}},"CP-APP-ENGINE-LOGS-STORAGE":{"locales":{"us":0.026},"properties":{}},"CP-APP-ENGINE-SSL-VIRTUAL-IP":{"locales":{"us":39},"properties":{}},"CP-CLOUD-DATASTORE-INSTANCES":{"locales":{"us":0.18},"properties":{}},"CP-CLOUD-DATASTORE-WRITE-OP":{"locales":{"us":6e-7},"properties":{}},"CP-CLOUD-DATASTORE-READ-OP":{"locales":{"us":6e-7},"properties":{}},"CP-CLOUD-DATASTORE-ENTITY-READ":{"locales":{"us":6e-7},"properties":{}},"CP-CLOUD-DATASTORE-ENTITY-WRITE":{"locales":{"us":0.0000018},"properties":{}},"CP-CLOUD-DATASTORE-ENTITY-DELETE":{"locales":{"us":2e-7},"properties":{}},"CP-PREDICTION-BULK-TRAINING":{"locales":{"us":0.002},"properties":{}},"CP-GENOMICS-STORAGE":{"locales":{"us":0.022},"properties":{}},"CP-GENOMICS-QUERIES":{"locales":{"us":1},"properties":{}},"CP-DATAFLOW-BATCH-VCPU":{"locales":{"us":0.056,"europe":0.059,"asia":0.059},"properties":{}},"CP-DATAFLOW-STREAMING-VCPU":{"locales":{"us":0.069,"europe":0.072,"asia":0.072},"properties":{}},"CP-DATAFLOW-BATCH-MEMORY":{"locales":{"us":0.003557,"europe":0.004172,"asia":0.004172},"properties":{}},"CP-DATAFLOW-STREAMING-MEMORY":{"locales":{"us":0.003557,"europe":0.004172,"asia":0.004172},"properties":{}},"CP-DATAFLOW-BATCH-STORAGE-PD":{"locales":{"us":0.000054,"europe":0.000054,"asia":0.000054},"properties":{}},"CP-DATAFLOW-STREAMING-STORAGE-PD":{"locales":{"us":0.000054,"europe":0.000054,"asia":0.000054},"properties":{}},"CP-DATAFLOW-BATCH-STORAGE-PD-SSD":{"locales":{"us":0.000298,"europe":0.000298,"asia":0.000298},"properties":{}},"CP-DATAFLOW-STREAMING-STORAGE-PD-SSD":{"locales":{"us":0.000298,"europe":0.000298,"asia":0.000298},"properties":{}},"CP-BIGTABLE-NODES":{"locales":{"us":0.65},"properties":{}},"CP-BIGTABLE-SSD":{"locales":{"us":0.17},"properties":{}},"CP-BIGTABLE-HDD":{"locales":{"us":0.026},"properties":{}},"CP-COMPUTEENGINE-STATIC-IP-CHARGE":{"locales":{"us":0.01},"properties":{}},"CP-COMPUTEENGINE-VPN":{"locales":{"us":0.05},"properties":{}},"CP-DATAPROC":{"locales":{"us":0.01},"properties":{}},"CP-CONTAINER-ENGINE-BASIC":{"locales":{"us":0,"us-central1":0,"us-east1":0,"us-east4":0,"us-west1":0,"europe":0,"europe-west1":0,"europe-west2":0,"europe-west3":0,"europe-west4":0,"northamerica-northeast1":0,"asia":0,"asia-east":0,"asia-northeast":0,"asia-southeast":0,"australia-southeast1":0,"australia":0,"southamerica-east1":0,"asia-south1":0},"properties":{}},"CP-CONTAINER-ENGINE-STANDARD":{"locales":{"us":0,"us-central1":0,"us-east1":0,"us-east4":0,"us-west1":0,"europe":0,"europe-west1":0,"europe-west2":0,"europe-west3":0,"europe-west4":0,"northamerica-northeast1":0,"asia":0,"asia-east":0,"asia-northeast":0,"asia-southeast":0,"australia-southeast1":0,"australia":0,"southamerica-east1":0,"asia-south1":0},"properties":{}},"CP-SUPPORT-BRONZE":{"locales":{"us":0},"properties":{}},"CP-SUPPORT-SILVER":{"locales":{"us":150},"properties":{}},"CP-SUPPORT-GOLD":{"locales":{"us":400},"properties":{}},"CP-COMPUTEENGINE-CUSTOM-VM-CORE":{"locales":{"us":0.033174,"us-central1":0.033174,"us-east1":0.033174,"us-east4":0.037364,"us-west1":0.033174,"europe":0.036489,"europe-west1":0.036489,"europe-west2":0.040692,"europe-west3":0.040692,"europe-west4":0.034802,"northamerica-northeast1":0.034802,"asia":0.03841,"asia-east":0.03841,"asia-northeast":0.040618,"asia-southeast":0.038996,"australia-southeast1":0.04488,"australia":0.04488,"southamerica-east1":0.05019,"asia-south1":0.037966},"properties":{}},"CP-COMPUTEENGINE-CUSTOM-VM-RAM":{"locales":{"us":0.004446,"us-central1":0.004446,"us-east1":0.004446,"us-east4":0.005008,"us-west1":0.004446,"europe":0.004892,"europe-west1":0.004892,"europe-west2":0.005453,"europe-west3":0.005453,"europe-west4":0.004664,"northamerica-northeast1":0.004664,"asia":0.00515,"asia-east":0.00515,"asia-northeast":0.005418,"asia-southeast":0.005226,"australia-southeast1":0.00601,"australia":0.00601,"southamerica-east1":0.006729,"asia-south1":0.005088},"properties":{}},"CP-COMPUTEENGINE-CUSTOM-VM-EXTENDED-RAM":{"locales":{"us":0.00955,"us-central1":0.00955,"us-east1":0.00955,"us-east4":0.010756,"us-west1":0.00955,"europe":0.010506,"europe-west1":0.010506,"europe-west2":0.01171,"europe-west3":0.01171,"europe-west4":0.010018,"northamerica-northeast1":0.010018,"asia":0.011059,"asia-east":0.011059,"asia-northeast":0.011667,"asia-southeast":0.011667,"australia-southeast1":0.01291,"australia":0.01291,"southamerica-east1":0.014451,"asia-south1":0.010929},"properties":{}},"CP-COMPUTEENGINE-PREDEFINED-VM-CORE":{"locales":{"us":0.031611,"us-central1":0.031611,"us-east1":0.031611,"us-east4":0.035605,"us-west1":0.031611,"europe":0.034773,"europe-west1":0.034773,"europe-west2":0.04073,"europe-west3":0.04073,"europe-west4":0.034773,"northamerica-northeast1":0.034773,"asia":0.036602,"asia-east":0.036602,"asia-northeast":0.040618,"asia-southeast":0.038999,"australia-southeast1":0.044856,"australia":0.044856,"southamerica-east1":0.0474165,"asia-south1":0.0378409},"properties":{}},"CP-COMPUTEENGINE-PREDEFINED-VM-RAM":{"locales":{"us":0.004237,"us-central1":0.004237,"us-east1":0.004237,"us-east4":0.005605,"us-west1":0.004237,"europe":0.004661,"europe-west1":0.004661,"europe-west2":0.005411,"europe-west3":0.005411,"europe-west4":0.004661,"northamerica-northeast1":0.004661,"asia":0.004906,"asia-east":0.004906,"asia-northeast":0.005419,"asia-southeast":0.005222,"australia-southeast1":0.006048,"australia":0.006048,"southamerica-east1":0.0063555,"asia-south1":0.005109},"properties":{}},"CP-COMPUTEENGINE-CUSTOM-VM-CORE-PREEMPTIBLE":{"locales":{"us":0.00698,"us-central1":0.00698,"us-east1":0.00698,"us-east4":0.007469,"us-west1":0.00698,"europe":0.00768,"europe-west1":0.00768,"europe-west2":0.00815,"europe-west3":0.00815,"europe-west4":0.007325,"northamerica-northeast1":0.007325,"asia":0.00768,"asia-east":0.00768,"asia-northeast":0.00883,"asia-southeast":0.007801,"australia-southeast1":0.00898,"australia":0.00898,"southamerica-east1":0.010038,"asia-south1":0.007992},"properties":{}},"CP-COMPUTEENGINE-CUSTOM-VM-RAM-PREEMPTIBLE":{"locales":{"us":0.00094,"us-central1":0.00094,"us-east1":0.00094,"us-east4":0.001006,"us-west1":0.00094,"europe":0.00103,"europe-west1":0.00103,"europe-west2":0.00109,"europe-west3":0.00109,"europe-west4":0.000987,"northamerica-northeast1":0.000987,"asia":0.00103,"asia-east":0.00103,"asia-northeast":0.001178,"asia-southeast":0.001045,"australia-southeast1":0.0012,"australia":0.0012,"southamerica-east1":0.001346,"asia-south1":0.001076},"properties":{}},"CP-COMPUTEENGINE-CUSTOM-VM-EXTENDED-RAM-PREEMPTIBLE":{"locales":{"us":0.002014,"us-central1":0.002014,"us-east1":0.002014,"us-east4":0.002155,"us-west1":0.002014,"europe":0.002212,"europe-west1":0.002212,"europe-west2":0.00235,"europe-west3":0.00235,"europe-west4":0.002114,"northamerica-northeast1":0.002114,"asia":0.002212,"asia-east":0.002212,"asia-northeast":0.002536,"asia-southeast":0.002536,"australia-southeast1":0.00258,"australia":0.00258,"southamerica-east1":0.00289,"asia-south1":0.002306},"properties":{}},"CP-COMPUTEENGINE-PREDEFINED-VM-CORE-PREEMPTIBLE":{"locales":{"us":0.0066551,"us-central1":0.006655,"us-east1":0.006655,"us-east4":0.00712085,"us-west1":0.006655,"europe":0.007321,"europe-west1":0.007321,"europe-west2":0.00815,"europe-west3":0.00815,"europe-west4":0.007321,"northamerica-northeast1":0.007321,"asia":0.00732,"asia-east":0.00732,"asia-northeast":0.00883,"asia-southeast":0.0078,"australia-southeast1":0.0089,"australia":0.0089,"southamerica-east1":0.00998265,"asia-south1":0.0080004},"properties":{}},"CP-COMPUTEENGINE-PREDEFINED-VM-RAM-PREEMPTIBLE":{"locales":{"us":0.000892,"us-central1":0.000892,"us-east1":0.000892,"us-east4":0.00095444,"us-west1":0.000892,"europe":0.000981,"europe-west1":0.000981,"europe-west2":0.00109,"europe-west3":0.00109,"europe-west4":0.000981,"northamerica-northeast1":0.000981,"asia":0.000981,"asia-east":0.000981,"asia-northeast":0.001178,"asia-southeast":0.00105,"australia-southeast1":0.0012,"australia":0.0012,"southamerica-east1":0.001338,"asia-south1":0.00107454},"properties":{}},"CP-DB-F1-MICRO":{"locales":{"us":0.015,"us-central1":0.015,"us-east1":0.015,"us-east4":0.0161,"us-west1":0.015,"europe":0.015,"europe-west1":0.015,"europe-west2":0.018,"europe-west3":0.018,"europe-west4":0.0165,"northamerica-northeast1":0.0165,"asia":0.015,"asia-east":0.015,"asia-northeast":0.0195,"asia-southeast":0,"australia-southeast1":0.0203,"australia":0.0203,"southamerica-east1":0.0255,"asia-south1":0.018},"properties":{}},"CP-DB-G1-SMALL":{"locales":{"us":0.05,"us-central1":0.05,"us-east1":0.05,"us-east4":0.0535,"us-west1":0.05,"europe":0.05,"europe-west1":0.05,"europe-west2":0.06,"europe-west3":0.06,"europe-west4":0.055,"northamerica-northeast1":0.055,"asia":0.05,"asia-east":0.05,"asia-northeast":0.065,"asia-southeast":0,"australia-southeast1":0.0675,"australia":0.0675,"southamerica-east1":0.075,"asia-south1":0.06},"properties":{}},"CP-DB-N1-STANDARD-1":{"locales":{"us":0.0965,"us-central1":0.0965,"us-east1":0.0965,"us-east4":0.1033,"us-west1":0.0965,"europe":0.0965,"europe-west1":0.0965,"europe-west2":0.1158,"europe-west3":0.1158,"europe-west4":0.1062,"northamerica-northeast1":0.1062,"asia":0.0965,"asia-east":0.0965,"asia-northeast":0.1255,"asia-southeast":0,"australia-southeast1":0.1303,"australia":0.1303,"southamerica-east1":0.1448,"asia-south1":0.1158},"properties":{}},"CP-DB-N1-STANDARD-2":{"locales":{"us":0.193,"us-central1":0.193,"us-east1":0.193,"us-east4":0.2065,"us-west1":0.193,"europe":0.193,"europe-west1":0.193,"europe-west2":0.2316,"europe-west3":0.2316,"europe-west4":0.2123,"northamerica-northeast1":0.2123,"asia":0.193,"asia-east":0.193,"asia-northeast":0.2509,"asia-southeast":0,"australia-southeast1":0.2606,"australia":0.2606,"southamerica-east1":0.2895,"asia-south1":0.2316},"properties":{}},"CP-DB-N1-STANDARD-4":{"locales":{"us":0.386,"us-central1":0.386,"us-east1":0.386,"us-east4":0.413,"us-west1":0.386,"europe":0.386,"europe-west1":0.386,"europe-west2":0.4632,"europe-west3":0.4632,"europe-west4":0.4246,"northamerica-northeast1":0.4246,"asia":0.386,"asia-east":0.386,"asia-northeast":0.5018,"asia-southeast":0,"australia-southeast1":0.5211,"australia":0.5211,"southamerica-east1":0.579,"asia-south1":0.4632},"properties":{}},"CP-DB-N1-STANDARD-8":{"locales":{"us":0.772,"us-central1":0.772,"us-east1":0.772,"us-east4":0.826,"us-west1":0.772,"europe":0.772,"europe-west1":0.772,"europe-west2":0.9264,"europe-west3":0.9264,"europe-west4":0.8492,"northamerica-northeast1":0.8492,"asia":0.772,"asia-east":0.772,"asia-northeast":1.0036,"asia-southeast":0,"australia-southeast1":1.0422,"australia":1.0422,"southamerica-east1":1.158,"asia-south1":0.9264},"properties":{}},"CP-DB-N1-STANDARD-16":{"locales":{"us":1.5445,"us-central1":1.5445,"us-east1":1.5445,"us-east4":1.6526,"us-west1":1.5445,"europe":1.5445,"europe-west1":1.5445,"europe-west2":1.8534,"europe-west3":1.8534,"europe-west4":1.6984,"northamerica-northeast1":1.6984,"asia":1.5445,"asia-east":1.5445,"asia-northeast":2.0079,"asia-southeast":0,"australia-southeast1":2.0851,"australia":2.0851,"southamerica-east1":2.3168,"asia-south1":1.8528},"properties":{}},"CP-DB-N1-STANDARD-32":{"locales":{"us":3.0885,"us-central1":3.0885,"us-east1":3.0885,"us-east4":3.3047,"us-west1":3.0885,"europe":3.0885,"europe-west1":3.0885,"europe-west2":3.7062,"europe-west3":3.7062,"europe-west4":3.3968,"northamerica-northeast1":3.3968,"asia":3.0885,"asia-east":3.0885,"asia-northeast":4.0151,"asia-southeast":0,"australia-southeast1":4.1695,"australia":4.1695,"southamerica-east1":4.6335,"asia-south1":3.7056},"properties":{}},"CP-DB-N1-STANDARD-64":{"locales":{"us":6.177,"us-central1":6.177,"us-east1":6.177,"us-east4":6.6094,"us-west1":6.177,"europe":6.177,"europe-west1":6.177,"europe-west2":7.4124,"europe-west3":7.4124,"europe-west4":6.7936,"northamerica-northeast1":6.7936,"asia":6.177,"asia-east":6.177,"asia-northeast":8.0301,"asia-southeast":0,"australia-southeast1":8.339,"australia":8.339,"southamerica-east1":9.2655,"asia-south1":7.4112},"properties":{}},"CP-DB-N1-HIGHMEM-2":{"locales":{"us":0.2515,"us-central1":0.2515,"us-east1":0.2515,"us-east4":0.2691,"us-west1":0.2515,"europe":0.2515,"europe-west1":0.2515,"europe-west2":0.3018,"europe-west3":0.3018,"europe-west4":0.2767,"northamerica-northeast1":0.2767,"asia":0.2515,"asia-east":0.2515,"asia-northeast":0.327,"asia-southeast":0,"australia-southeast1":0.3395,"australia":0.3395,"southamerica-east1":0.3773,"asia-south1":0.3018},"properties":{}},"CP-DB-N1-HIGHMEM-4":{"locales":{"us":0.503,"us-central1":0.503,"us-east1":0.503,"us-east4":0.5382,"us-west1":0.503,"europe":0.503,"europe-west1":0.503,"europe-west2":0.6036,"europe-west3":0.6036,"europe-west4":0.5533,"northamerica-northeast1":0.5533,"asia":0.503,"asia-east":0.503,"asia-northeast":0.6539,"asia-southeast":0,"australia-southeast1":0.6791,"australia":0.6791,"southamerica-east1":0.7545,"asia-south1":0.6036},"properties":{}},"CP-DB-N1-HIGHMEM-8":{"locales":{"us":1.006,"us-central1":1.006,"us-east1":1.006,"us-east4":1.0764,"us-west1":1.006,"europe":1.006,"europe-west1":1.006,"europe-west2":1.2072,"europe-west3":1.2072,"europe-west4":1.1066,"northamerica-northeast1":1.1066,"asia":1.006,"asia-east":1.006,"asia-northeast":1.3078,"asia-southeast":0,"australia-southeast1":1.3581,"australia":1.3581,"southamerica-east1":1.509,"asia-south1":1.2072},"properties":{}},"CP-DB-N1-HIGHMEM-16":{"locales":{"us":2.012,"us-central1":2.012,"us-east1":2.012,"us-east4":2.1528,"us-west1":2.012,"europe":2.012,"europe-west1":2.012,"europe-west2":2.4144,"europe-west3":2.4144,"europe-west4":2.2132,"northamerica-northeast1":2.2132,"asia":2.012,"asia-east":2.012,"asia-northeast":2.6156,"asia-southeast":0,"australia-southeast1":2.7162,"australia":2.7162,"southamerica-east1":3.018,"asia-south1":2.4144},"properties":{}},"CP-DB-N1-HIGHMEM-32":{"locales":{"us":4.024,"us-central1":4.024,"us-east1":4.024,"us-east4":4.3057,"us-west1":4.024,"europe":4.024,"europe-west1":4.024,"europe-west2":4.8288,"europe-west3":4.8288,"europe-west4":4.4264,"northamerica-northeast1":4.4264,"asia":4.024,"asia-east":4.024,"asia-northeast":5.2312,"asia-southeast":0,"australia-southeast1":5.4324,"australia":5.4324,"southamerica-east1":6.036,"asia-south1":4.8288},"properties":{}},"CP-DB-N1-HIGHMEM-64":{"locales":{"us":8.048,"us-central1":8.048,"us-east1":8.048,"us-east4":8.6114,"us-west1":8.048,"europe":8.048,"europe-west1":8.048,"europe-west2":9.6576,"europe-west3":9.6576,"europe-west4":8.8528,"northamerica-northeast1":8.8528,"asia":8.048,"asia-east":8.048,"asia-northeast":10.4624,"asia-southeast":0,"australia-southeast1":10.8648,"australia":10.8648,"southamerica-east1":12.072,"asia-south1":9.6576},"properties":{}},"CP-CLOUDSQL-STORAGE-SSD":{"locales":{"us":0.17,"us-central1":0.17,"us-east1":0.17,"us-east4":0.1819,"us-west1":0.17,"europe":0.17,"europe-west1":0.17,"europe-west2":0.204,"europe-west3":0.204,"europe-west4":0.187,"northamerica-northeast1":0.187,"asia":0.17,"asia-east":0.17,"asia-northeast":0.22,"asia-southeast":0,"australia-southeast1":0.23,"australia":0.23,"southamerica-east1":0.255,"asia-south1":0.204},"properties":{}},"CP-CLOUDSQL-STORAGE-HDD":{"locales":{"us":0.09,"us-central1":0.09,"us-east1":0.09,"us-east4":0.0963,"us-west1":0.09,"europe":0.09,"europe-west1":0.09,"europe-west2":0.108,"europe-west3":0.108,"europe-west4":0.099,"northamerica-northeast1":0.099,"asia":0.09,"asia-east":0.09,"asia-northeast":0.12,"asia-southeast":0,"australia-southeast1":0.122,"australia":0.122,"southamerica-east1":0.135,"asia-south1":0.108},"properties":{}},"CP-CLOUDSQL-BACKUP":{"locales":{"us":0.08,"us-central1":0.08,"us-east1":0.08,"us-east4":0.0856,"us-west1":0.08,"europe":0.08,"europe-west1":0.08,"europe-west2":0.096,"europe-west3":0.096,"europe-west4":0.088,"northamerica-northeast1":0.088,"asia":0.08,"asia-east":0.08,"asia-northeast":0.1,"asia-southeast":0,"australia-southeast1":0.108,"australia":0.108,"southamerica-east1":0.12,"asia-south1":0.096},"properties":{}},"CP-STACKDRIVER-MONITORED-RESOURCES":{"locales":{"us":8},"properties":{}},"CP-STACKDRIVER-LOGS-VOLUME":{"locales":{"us":0.5},"properties":{}},"CP-STACKDRIVER-METRICS-DESCRIPTION":{"locales":{"us":1},"properties":{}},"CP-STACKDRIVER-TIME-SERIES":{"locales":{"us":0.1},"properties":{}},"CP-CLOUDCDN-CACHE-FILL-INTRA-APAC":{"locales":{"us":0.06},"properties":{}},"CP-CLOUDCDN-CACHE-FILL-INTRA-EU":{"locales":{"us":0.05},"properties":{}},"CP-CLOUDCDN-CACHE-FILL-INTRA-NA":{"locales":{"us":0.04},"properties":{}},"CP-CLOUDCDN-CACHE-FILL-INTER-AU":{"locales":{"us":0.15},"properties":{}},"CP-CLOUDCDN-CACHE-FILL-INTER-OTHER":{"locales":{"us":0.08},"properties":{}},"CP-CLOUDCDN-CACHE-LOOKUP-REQUESTS":{"locales":{"us":7.5e-7},"properties":{}},"CP-CLOUDCDN-CACHE-INVALIDATION":{"locales":{"us":0.005},"properties":{}},"CP-ML-TRAINING":{"locales":{"us":0.49,"europe":0.54,"asia":0.54},"properties":{}},"CP-ML-PREDICTION-ONLINE":{"locales":{"us":0.3,"europe":0.348,"asia":0.348},"properties":{}},"CP-ML-PREDICTION-PROCESSING":{"locales":{"us":0.4,"europe":0.44,"asia":0.44},"properties":{}},"CP-ML-PREDICTION-BATCH":{"locales":{"us":0.09262,"europe":0.10744,"asia":0.10744},"properties":{}},"CP-BIGSTORE-STORAGE-COLDLINE":{"locales":{"us":0.007,"us-central1":0.007,"us-east1":0.007,"us-east4":0.01,"us-west1":0.007,"europe":0.007,"europe-west1":0.007,"europe-west2":0.013,"europe-west3":0.013,"europe-west4":0.007,"northamerica-northeast1":0.013,"asia-east":0.007,"asia-northeast":0.01,"australia-southeast1":0.013,"australia":0.013,"southamerica-east1":0.014,"asia-south1":0.013},"properties":{}},"CP-BIGSTORE-DATA-RETRIEVAL-COLDLINE":{"locales":{"us":0.05},"properties":{}},"CP-BIGSTORE-STORAGE-MULTI_REGIONAL":{"locales":{"us":0.026,"us-central1":0.026,"us-east1":0.026,"us-east4":0.026,"us-west1":0.026,"europe":0.026,"europe-west1":0.026,"europe-west2":0.026,"europe-west3":0.026,"europe-west4":0.026,"northamerica-northeast1":0.026,"asia-east":0.026,"asia-northeast":0.026,"australia-southeast1":0.026,"australia":0.026,"southamerica-east1":0.026,"asia-south1":0.026},"properties":{}},"CP-BIGSTORE-STORAGE-REGIONAL":{"locales":{"us":0.02,"us-central1":0.02,"us-east1":0.02,"us-east4":0.023,"us-west1":0.02,"europe":0.02,"europe-west1":0.02,"europe-west2":0.023,"europe-west3":0.023,"europe-west4":0.02,"northamerica-northeast1":0.023,"asia-east":0.02,"asia-northeast":0.023,"australia-southeast1":0.023,"australia":0.023,"southamerica-east1":0.035,"asia-south1":0.023},"properties":{}},"CP-BIGSTORE-STORAGE-NEARLINE":{"locales":{"us":0.01,"us-central1":0.01,"us-east1":0.01,"us-east4":0.016,"us-west1":0.01,"europe":0.01,"europe-west1":0.01,"europe-west2":0.016,"europe-west3":0.016,"europe-west4":0.01,"northamerica-northeast1":0.016,"asia-east":0.01,"asia-northeast":0.016,"australia-southeast1":0.016,"australia":0.016,"southamerica-east1":0.02,"asia-south1":0.016},"properties":{}},"CP-GAE-FLEX-INSTANCE-CORE-HOURS":{"locales":{"us":0.0526},"properties":{}},"CP-GAE-FLEX-INSTANCE-RAM":{"locales":{"us":0.0071},"properties":{}},"CP-GAE-FLEX-STORAGE-PD-CAPACITY":{"locales":{"us":0.04},"properties":{}},"CP-KMS-KEY-VERSION":{"locales":{"us":0.06},"properties":{}},"CP-KMS-CRYPTO-OPERATION":{"locales":{"us":0.000003},"properties":{}},"GPU_NVIDIA_TESLA_K80":{"locales":{"us":0.45,"us-central1":0.45,"us-east1":0.45,"us-east4":0,"us-west1":0.45,"europe":0.49,"europe-west1":0.49,"europe-west2":0,"europe-west3":0,"europe-west4":0,"northamerica-northeast1":0,"asia-east":0.49,"asia-northeast":0,"asia-southeast":0,"australia-southeast1":0,"australia":0,"southamerica-east1":0,"asia-south1":0},"properties":{}},"GPU_NVIDIA_TESLA_P100":{"locales":{"us":1.46,"us-central1":1.46,"us-east1":1.46,"us-east4":0,"us-west1":1.46,"europe":1.6,"europe-west1":1.6,"europe-west2":0,"europe-west3":0,"europe-west4":0,"northamerica-northeast1":0,"asia-east":1.6,"asia-northeast":0,"asia-southeast":0,"australia-southeast1":0,"australia":0,"southamerica-east1":0,"asia-south1":0},"properties":{}},"GPU_NVIDIA_TESLA_K80-PREEMPTIBLE":{"locales":{"us":0.22,"us-central1":0.22,"us-east1":0.22,"us-east4":0,"us-west1":0.22,"europe":0.22,"europe-west1":0.22,"europe-west2":0,"europe-west3":0,"europe-west4":0,"northamerica-northeast1":0,"asia-east":0.22,"asia-northeast":0,"asia-southeast":0,"australia-southeast1":0,"australia":0,"southamerica-east1":0,"asia-south1":0},"properties":{}},"GPU_NVIDIA_TESLA_P100-PREEMPTIBLE":{"locales":{"us":0.73,"us-central1":0.73,"us-east1":0.73,"us-east4":0,"us-west1":0.73,"europe":0.73,"europe-west1":0.73,"europe-west2":0,"europe-west3":0,"europe-west4":0,"northamerica-northeast1":0,"asia-east":0.73,"asia-northeast":0,"asia-southeast":0,"australia-southeast1":0,"australia":0,"southamerica-east1":0,"asia-south1":0},"properties":{}},"CP-SPANNER-NODE":{"locales":{"us":0.9,"us-central1":0.9,"europe-west1":0.9,"asia-east1":0.9,"asia-northeast1":1.17,"nam3":3,"nam-eur-asia1":9},"properties":{}},"CP-SPANNER-STORAGE-SSD":{"locales":{"us":0.3,"us-central1":0.3,"europe-west1":0.3,"asia-east1":0.3,"asia-northeast1":0.39,"nam3":0.5,"nam-eur-asia1":0.9},"properties":{}},"CP-PROF-SVC-START":{"locales":{"us":25000},"properties":{}},"CP-PROF-SVC-SPRINT":{"locales":{"us":125000},"properties":{}},"CP-PROF-SVC-PLAN-INF":{"locales":{"us":120000},"properties":{}},"CP-PROF-SVC-PLAN-DA":{"locales":{"us":120000},"properties":{}},"CP-PROF-SVC-PLAN-ML":{"locales":{"us":80000},"properties":{}},"CP-PROF-SVC-PLAN-APP":{"locales":{"us":120000},"properties":{}},"GAPPS-PROF-SVC-ADA":{"locales":{"us":150000},"properties":{}},"GAPPS-PROF-SVC-CMAS":{"locales":{"us":25000},"properties":{}},"GAPPS-PROF-SVC-PSC":{"locales":{"us":30000},"properties":{}},"GAPPS-PROF-SVC-SA":{"locales":{"us":30000},"properties":{}},"GAPPS-PROF-SVC-TSP":{"locales":{"us":25000},"properties":{}},"CP-PROF-SVC-TAM":{"locales":{"us":12500},"properties":{}},"CP-NEW-SUPPORT-USERS-DEVELOPMENT":{"locales":{"us":100},"properties":{}},"CP-NEW-SUPPORT-USERS-PRODUCTION":{"locales":{"us":250},"properties":{}},"CP-NEW-SUPPORT-USERS-ON-CALL":{"locales":{"us":1500},"properties":{}},"CP-DB-PG-F1-MICRO":{"locales":{"us":0.015,"us-central1":0.015,"us-east1":0.015,"us-east4":0.0161,"us-west1":0.015,"europe":0.015,"europe-west1":0.015,"europe-west2":0.018,"europe-west3":0.018,"europe-west4":0.0165,"northamerica-northeast1":0.0165,"asia":0.015,"asia-east":0.015,"asia-northeast":0.0195,"asia-southeast":0,"australia-southeast1":0.0203,"australia":0.0203,"southamerica-east1":0.0225,"asia-south1":0.0018},"properties":{}},"CP-DB-PG-G1-SMALL":{"locales":{"us":0.05,"us-central1":0.05,"us-east1":0.05,"us-east4":0.0535,"us-west1":0.05,"europe":0.05,"europe-west1":0.05,"europe-west2":0.06,"europe-west3":0.06,"europe-west4":0.055,"northamerica-northeast1":0.055,"asia":0.05,"asia-east":0.05,"asia-northeast":0.065,"asia-southeast":0,"australia-southeast1":0.0675,"australia":0.0675,"southamerica-east1":0.075,"asia-south1":0.06},"properties":{}},"CP-DB-PG-CUSTOM-VM-CORE":{"locales":{"us":0.059,"us-central1":0.059,"us-east1":0.059,"us-east4":0.0631,"us-west1":0.059,"europe":0.059,"europe-west1":0.059,"europe-west2":0.0708,"europe-west3":0.0708,"europe-west4":0.0649,"northamerica-northeast1":0.0649,"asia":0.059,"asia-east":0.059,"asia-northeast":0.0767,"asia-southeast":0,"australia-southeast1":0.0797,"australia":0.0797,"southamerica-east1":0.0885,"asia-south1":0.0708},"properties":{}},"CP-DB-PG-CUSTOM-VM-RAM":{"locales":{"us":0.01,"us-central1":0.01,"us-east1":0.01,"us-east4":0.0107,"us-west1":0.01,"europe":0.01,"europe-west1":0.01,"europe-west2":0.012,"europe-west3":0.012,"europe-west4":0.011,"northamerica-northeast1":0.011,"asia":0.01,"asia-east":0.01,"asia-northeast":0.013,"asia-southeast":0,"australia-southeast1":0.0135,"australia":0.0135,"southamerica-east1":0.015,"asia-south1":0.012},"properties":{}},"CP-CUD-1-YEAR-CPU":{"locales":{"us":0.019915,"us-central1":0.019915,"us-east1":0.019915,"us-east4":0.021309,"us-west1":0.019915,"europe":0.021907,"europe-west1":0.021907,"europe-west2":0.025636,"europe-west3":0.025636,"europe-west4":0.021925,"northamerica-northeast1":0.021925,"asia-east":0.023059,"asia-northeast":0.025589,"asia-southeast":0.024567,"australia-southeast1":0.028274,"australia":0.028274,"southamerica-east1":0.03162,"asia-south1":0.023919},"properties":{}},"CP-CUD-1-YEAR-RAM":{"locales":{"us":0.002669,"us-central1":0.002669,"us-east1":0.002669,"us-east4":0.002856,"us-west1":0.002669,"europe":0.002936,"europe-west1":0.002936,"europe-west2":0.003435,"europe-west3":0.003435,"europe-west4":0.002938,"northamerica-northeast1":0.002938,"asia-east":0.003091,"asia-northeast":0.003414,"asia-southeast":0.003292,"australia-southeast1":0.003786,"australia":0.003786,"southamerica-east1":0.004239,"asia-south1":0.003205},"properties":{}},"CP-CUD-3-YEAR-CPU":{"locales":{"us":0.014225,"us-central1":0.014225,"us-east1":0.014225,"us-east4":0.015221,"us-west1":0.014225,"europe":0.015648,"europe-west1":0.015648,"europe-west2":0.0183114,"europe-west3":0.0183114,"europe-west4":0.015661,"northamerica-northeast1":0.015661,"asia-east":0.016471,"asia-northeast":0.018278,"asia-southeast":0.017548,"australia-southeast1":0.020196,"australia":0.020196,"southamerica-east1":0.0225855,"asia-south1":0.017085},"properties":{}},"CP-CUD-3-YEAR-RAM":{"locales":{"us":0.001907,"us-central1":0.001907,"us-east1":0.001907,"us-east4":0.00204,"us-west1":0.001907,"europe":0.002097,"europe-west1":0.002097,"europe-west2":0.0024539,"europe-west3":0.0024539,"europe-west4":0.002099,"northamerica-northeast1":0.002099,"asia-east":0.002208,"asia-northeast":0.002438,"asia-southeast":0.002352,"australia-southeast1":0.0027045,"australia":0.0027045,"southamerica-east1":0.0030281,"asia-south1":0.00229},"properties":{}},"CP-DATAPREP-UNITS":{"locales":{"us-central1":0.096},"properties":{}},"CP-CLOUD-TPU":{"locales":{"us-central1":6.5},"properties":{}}}},"crawled_at":1524642486260}]}